gethandledf/Eula.txt
gethandledf/README.md
gethandledf/__init__.py
gethandledf/handle.exe
gethandledf/handle64.exe
gethandledf/handle64a.exe
gethandledf/requirements.txt
gethandledf/thirdparty.json
gethandledf-0.11.dist-info/LICENSE.rst
gethandledf-0.11.dist-info/METADATA
gethandledf-0.11.dist-info/WHEEL
gethandledf-0.11.dist-info/top_level.txt
gethandledf-0.11.dist-info/RECORD
