Metadata-Version: 2.1
Name: gethandledf
Version: 0.11
Summary: Retrieves the list of handles using the 'handle.exe' command and return the data as a pandas DataFrame.
Home-page: https://github.com/hansalemaos/gethandledf
Author: Johannes Fischer
Author-email: aulasparticularesdealemaosp@gmail.com
License: MIT
Keywords: wmic,process,pid,handle
Classifier: Development Status :: 4 - Beta
Classifier: Programming Language :: Python :: 3 :: Only
Classifier: Programming Language :: Python :: 3.10
Classifier: Topic :: Software Development :: Libraries :: Python Modules
Classifier: Topic :: Utilities
License-File: LICENSE.rst
Requires-Dist: getfilenuitkapython
Requires-Dist: kthread-sleep
Requires-Dist: numpy
Requires-Dist: pandas
Requires-Dist: subprocesskiller
